{
    "sourceFile": ".env",
    "activeCommit": 0,
    "commits": [
        {
            "activePatchIndex": 4,
            "patches": [
                {
                    "date": 1714972906900,
                    "content": "Index: \n===================================================================\n--- \n+++ \n"
                },
                {
                    "date": 1714972912691,
                    "content": "Index: \n===================================================================\n--- \n+++ \n@@ -6,8 +6,8 @@\n LOG_CHANNEL=stack\r\n DB_CONNECTION=mysql\r\n DB_HOST=127.0.0.1\r\n DB_PORT=3306\r\n-DB_DATABASE=ims\r\n+DB_DATABASE=\r\n DB_USERNAME=root\r\n DB_PASSWORD=\r\n PURCHASECODE=8677075b-8e04-49a5-b2aa-31478442d9fd\n\\ No newline at end of file\n"
                },
                {
                    "date": 1714972924059,
                    "content": "Index: \n===================================================================\n--- \n+++ \n@@ -6,8 +6,8 @@\n LOG_CHANNEL=stack\r\n DB_CONNECTION=mysql\r\n DB_HOST=127.0.0.1\r\n DB_PORT=3306\r\n-DB_DATABASE=\r\n+DB_DATABASE= warehouse\r\n DB_USERNAME=root\r\n DB_PASSWORD=\r\n PURCHASECODE=8677075b-8e04-49a5-b2aa-31478442d9fd\n\\ No newline at end of file\n"
                },
                {
                    "date": 1714977157624,
                    "content": "Index: \n===================================================================\n--- \n+++ \n@@ -1,13 +1,13 @@\n APP_NAME=Torylab\r\n APP_ENV=production\r\n-APP_KEY=base64:BO5Y8C6UtqwRtky57Q9pCHARv0Lm87kjrE+atNtGDRs=\r\n+APP_KEY=base64:l/MH9gJoRxJkSNnFZME82eR3MtGghf0RzRvNbYhggaQ=\r\n APP_DEBUG=false\r\n APP_URL=http://ims.test/\r\n LOG_CHANNEL=stack\r\n DB_CONNECTION=mysql\r\n DB_HOST=127.0.0.1\r\n DB_PORT=3306\r\n-DB_DATABASE= warehouse\r\n+DB_DATABASE=warehouse\r\n DB_USERNAME=root\r\n DB_PASSWORD=\r\n PURCHASECODE=8677075b-8e04-49a5-b2aa-31478442d9fd\n\\ No newline at end of file\n"
                },
                {
                    "date": 1714977171960,
                    "content": "Index: \n===================================================================\n--- \n+++ \n@@ -1,8 +1,8 @@\n APP_NAME=Torylab\r\n APP_ENV=production\r\n APP_KEY=base64:l/MH9gJoRxJkSNnFZME82eR3MtGghf0RzRvNbYhggaQ=\r\n-APP_DEBUG=false\r\n+APP_DEBUG=faltruese\r\n APP_URL=http://ims.test/\r\n LOG_CHANNEL=stack\r\n DB_CONNECTION=mysql\r\n DB_HOST=127.0.0.1\r\n"
                }
            ],
            "date": 1714972906900,
            "name": "Commit-0",
            "content": "APP_NAME=Torylab\r\nAPP_ENV=production\r\nAPP_KEY=base64:BO5Y8C6UtqwRtky57Q9pCHARv0Lm87kjrE+atNtGDRs=\r\nAPP_DEBUG=false\r\nAPP_URL=http://ims.test/\r\nLOG_CHANNEL=stack\r\nDB_CONNECTION=mysql\r\nDB_HOST=127.0.0.1\r\nDB_PORT=3306\r\nDB_DATABASE=ims\r\nDB_USERNAME=root\r\nDB_PASSWORD=\r\nPURCHASECODE=8677075b-8e04-49a5-b2aa-31478442d9fd"
        }
    ]
}